partial_readonly.py
partial_readonly-0.0.3.dist-info/METADATA
partial_readonly-0.0.3.dist-info/RECORD
partial_readonly-0.0.3.dist-info/WHEEL
partial_readonly-0.0.3.dist-info/top_level.txt
