Metadata-Version: 2.1
Name: partial-readonly
Version: 0.0.3
Summary: make some of the dataclass fields read-only
Home-page: https://github.com/book987/partial_readonly
Author: book987
Author-email: book78987book@gmail.com
License: MIT
Keywords: dataclass readonly
Platform: UNKNOWN
Requires-Python: >=3.7
